[
    {"id" : 1, "nombre": "Taza Pokemon", "precio": 1299, "categoria": "tazas", "img": "multimedia/productos/tazas/taza-pokemon.png", "stock": 8, "detalle": "Taza pokemon", "cantidad": 1 },
    {"id": 2, "nombre": "Taza Naruto", "precio": 1299, "categoria": "tazas", "img": "multimedia/productos/tazas/taza-naruto.png", "stock": 5, "detalle": "taza ninja", "cantidad": 1  },
    {"id": 3, "nombre": "Taza Hunter", "precio": 1299, "categoria": "tazas", "img": "multimedia/productos/tazas/taza-hunter.png", "stock": 9 ,"detalle": "taza cazador" , "cantidad": 1},
    {"id": 4, "nombre": "Taza Demon", "precio": 1299, "categoria": "tazas", "img": "multimedia/productos/tazas/taza-demon.png", "stock": 10 , "detalle": "taza demon" , "cantidad": 1},
    {"id": 5, "nombre": "Taza Sailor", "precio": 1299, "categoria": "tazas", "img": "multimedia/productos/tazas/taza-sailor.png", "stock": 8, "detalle": "taza lunar", "cantidad": 1 },
    {"id": 6, "nombre": "Auricular Gatos", "precio": 12999, "categoria": "accesorios", "img": "multimedia/productos/accesorios/gato_muestra.png", "stock": 5, "detalle": "Auricular Gatos RGB", "cantidad": 1  },
    {"id": 7, "nombre": "Cartera Sailor", "precio": 13999, "categoria": "accesorios", "img": "multimedia/productos/accesorios/cartera.png", "stock": 9 ,"detalle": "Cartera lunar" , "cantidad": 1},
    {"id": 8, "nombre": "Lapiz Kawaii", "precio": 999, "categoria": "accesorios", "img": "multimedia/productos/accesorios/lapiz.png", "stock": 9 ,"detalle": "lapiz osito" , "cantidad": 1},
    {"id": 9, "nombre": "Cuaderno Avocado", "precio": 1499, "categoria": "accesorios", "img": "multimedia/productos/accesorios/cuaderno.png", "stock": 9 ,"detalle": "cuaderno mas tierno" , "cantidad": 1},
    {"id": 10, "nombre": "Naruto", "precio": 1599, "categoria": "manga", "img": "multimedia/productos/tomos/naruto_tomos.png", "stock": 9 ,"detalle": "Ninja" , "cantidad": 1},
    {"id": 11, "nombre": "Berserck", "precio": 2099, "categoria": "manga", "img": "multimedia/productos/tomos/tomos-bers.png", "stock": 9 ,"detalle": "El mejor manga" , "cantidad": 1},
    {"id": 12, "nombre": "Claymore", "precio": 599, "categoria": "manga", "img": "multimedia/productos/tomos/tomos-clay.png", "stock": 9 ,"detalle": "Tomos Varios" , "cantidad": 1},
    {"id": 13, "nombre": "Dr Stone", "precio": 999, "categoria": "manga", "img": "multimedia/productos/tomos/tomos-dr.png", "stock": 9 ,"detalle": "Ciencia" , "cantidad": 1},
    {"id": 14, "nombre": "Elfend Lied", "precio": 599, "categoria": "manga", "img": "multimedia/productos/tomos/tomos-elfen.png", "stock": 9 ,"detalle": "Sobrenatural" , "cantidad": 1},
    {"id": 15, "nombre": "Hunter X", "precio": 599, "categoria": "manga", "img": "multimedia/productos/tomos/tomos-hunter.png", "stock": 9 ,"detalle": "Hunter X hunter" , "cantidad": 1},
    {"id": 16, "nombre": "One Punch Man", "precio": 899, "categoria": "manga", "img": "multimedia/productos/tomos/tomos-one.png", "stock": 9 ,"detalle": "Sopa" , "cantidad": 1},
    {"id": 17, "nombre": "Promise Neverland", "precio": 1399, "categoria": "manga", "img": "multimedia/productos/tomos/tomos-promise.png", "stock": 9 ,"detalle": "Aventuras" , "cantidad": 1},
    {"id": 19, "nombre": "Remera Naruto", "precio": 1699, "categoria": "remeras", "img": "multimedia/productos/remeras/remera_naruto.png", "stock": 9 ,"detalle": "Talle Unico" , "cantidad": 1},
    {"id": 20, "nombre": "Remera Dr Stone", "precio": 1899, "categoria": "remeras", "img": "multimedia/productos/remeras/remera-dr.png", "stock": 9 ,"detalle": "Talle  M - L - XL" , "cantidad": 1},
    {"id": 21, "nombre": "Remera Dr Stone", "precio": 1699, "categoria": "remeras", "img": "multimedia/productos/remeras/remera-dr2.png", "stock": 9 ,"detalle": "Talle  XS - S - M" , "cantidad": 1},
    {"id": 18, "nombre": "Card Captors", "precio": 1199, "categoria": "manga", "img": "multimedia/productos/tomos/tomos-sakura.png", "stock": 9 ,"detalle": "Cartas Clow" , "cantidad": 1},
    {"id": 22, "nombre": "Remera Dragon", "precio": 1599, "categoria": "remeras", "img": "multimedia/productos/remeras/remera-dragon.png", "stock": 9 ,"detalle": "Talle  M - L - XL" , "cantidad": 1},
    {"id": 23, "nombre": "Remera Evangelion", "precio": 1999, "categoria": "remeras", "img": "multimedia/productos/remeras/remera-eva.png", "stock": 9 ,"detalle": "Talle  XS - S - M " , "cantidad": 1},  
    {"id": 24, "nombre": "Remera Anime", "precio": 599, "categoria": "remeras", "img": "multimedia/productos/remeras/remera-h.png", "stock": 9 ,"detalle": "Talle Unico" , "cantidad": 1},
    {"id": 25, "nombre": "Remera Hunter", "precio": 599, "categoria": "remeras", "img": "multimedia/productos/remeras/remera-hunter.png", "stock": 9 ,"detalle": "Talle  M - L - XL" , "cantidad": 1},
    {"id": 26, "nombre": "Remera Naruto", "precio": 1599, "categoria": "remeras", "img": "multimedia/productos/remeras/remera-naruto2.png", "stock": 9 ,"detalle": "Talle  M - L - XL" , "cantidad": 1},
    {"id": 27, "nombre": "Remera Promise", "precio": 2599, "categoria": "remeras", "img": "multimedia/productos/remeras/remera-promise.png", "stock": 9 ,"detalle": "Talle  XS - S - M" , "cantidad": 1},
    {"id": 28, "nombre": "Sailor Moon", "precio": 1599, "categoria": "remeras", "img": "multimedia/productos/remeras/remera-sailor.png", "stock": 9 ,"detalle": "Talle  XS - S - M" , "cantidad": 1}
] 
